LICENSE
MANIFEST.in
README.md
setup.py
mkTestCase/__init__.py
mkTestCase/mkTestCase.py
mkTestCase.egg-info/PKG-INFO
mkTestCase.egg-info/SOURCES.txt
mkTestCase.egg-info/dependency_links.txt
mkTestCase.egg-info/requires.txt
mkTestCase.egg-info/top_level.txt
mkTestCase/testcases/add.yml
mkTestCase/testcases/alert.yml
mkTestCase/testcases/allselect.yml
mkTestCase/testcases/authority.yml
mkTestCase/testcases/back.yml
mkTestCase/testcases/compatibility.yml
mkTestCase/testcases/concurrent.yml
mkTestCase/testcases/control.yml
mkTestCase/testcases/dataInput.yml
mkTestCase/testcases/dataOutput.yml
mkTestCase/testcases/delete.yml
mkTestCase/testcases/download.yml
mkTestCase/testcases/form.yml
mkTestCase/testcases/ip.yml
mkTestCase/testcases/list.yml
mkTestCase/testcases/login.yml
mkTestCase/testcases/modify.yml
mkTestCase/testcases/nav.yml
mkTestCase/testcases/page.yml
mkTestCase/testcases/pagination.yml
mkTestCase/testcases/print.yml
mkTestCase/testcases/regist.yml
mkTestCase/testcases/search.yml
mkTestCase/testcases/ui.yml
mkTestCase/testcases/upload.yml