Metadata-Version: 2.1
Name: mkTestCase
Version: 0.1.1
Summary: Write test cases like building blocks
Home-page: https://github.com/yongchin0821/mkTestCase
Author: Yongchin
Author-email: yongchin39@qq.com
License: MIT
Project-URL: Bug Tracker, https://github.com/yongchin0821/mkTestCase/issues
Keywords: testcase,automatically generate test cases,automated test
Classifier: Topic :: Software Development :: Testing
Classifier: Programming Language :: Python
Classifier: Operating System :: OS Independent
Classifier: License :: OSI Approved :: MIT License
Requires-Python: >=3.7
License-File: LICENSE
